AUTHORS
CHANGELOG.rst
CONTRIBUTORS
LICENSE
MANIFEST.in
README.md
requirements-dev.txt
requirements.txt
setup.py
djqdqtranslations/__init__.py
djqdqtranslations/tests.py
djqdqtranslations.egg-info/PKG-INFO
djqdqtranslations.egg-info/SOURCES.txt
djqdqtranslations.egg-info/dependency_links.txt
djqdqtranslations.egg-info/not-zip-safe
djqdqtranslations.egg-info/requires.txt
djqdqtranslations.egg-info/top_level.txt
djqdqtranslations/management/__init__.py
djqdqtranslations/management/commands/__init__.py
djqdqtranslations/management/commands/downloadtranslations.py
djqdqtranslations/management/commands/makethememessages.py
djqdqtranslations/management/commands/mergemessages.py
djqdqtranslations/management/commands/updatetranslations.py
djqdqtranslations/templatetags/__init__.py
djqdqtranslations/templatetags/translations.py