Metadata-Version: 1.1
Name: djqdqtranslations
Version: 0.6
Summary: Python django commands for crowding translations management
Home-page: https://gitlab.qdqmedia.com/shared-projects/djqdqtranslations.git
Author: QdqMedia Web Team
Author-email: equipo_web@qdqmedia.com
License: MIT License
Download-URL: https://gitlab.qdqmedia.com/shared-projects/djqdqtranslations/repository/archive.tar.bz2
Keywords: qdqmedia,translation,django
Platform: UNKNOWN
Classifier: Development Status :: 3 - Alpha
Classifier: Intended Audience :: Developers
Classifier: Natural Language :: English
Classifier: License :: OSI Approved :: MIT License
Classifier: Programming Language :: Python
